[{"id":"736d8e28.25a38","type":"tab","label":"Flow 2","disabled":false,"info":""},{"id":"dac5757c.95ff48","type":"debug","z":"736d8e28.25a38","name":"","active":true,"tosidebar":true,"console":false,"tostatus":false,"complete":"payload","targetType":"msg","x":588.6000576019287,"y":175.00000381469727,"wires":[]},{"id":"6a293e32.4eb5a","type":"ui_text","z":"736d8e28.25a38","group":"617960c6.f84cd","order":1,"width":0,"height":0,"name":"","label":"Status","format":"{{msg.payload}}","layout":"col-center","x":708.6000547409058,"y":280.80002784729004,"wires":[]},{"id":"5c282aca.7411a4","type":"function","z":"736d8e28.25a38","name":"","func":"var c=msg.payload.a;\nmsg.payload=\"Hii \"+ c +\" Your Form is Successfully Submitted\";\nreturn msg;","outputs":1,"noerr":0,"x":432,"y":279,"wires":[["6a293e32.4eb5a"]]},{"id":"64e1a975.4ae3b8","type":"ui_form","z":"736d8e28.25a38","name":"","label":"","group":"617960c6.f84cd","order":2,"width":0,"height":0,"options":[{"label":"Name","value":"a","type":"text","required":true,"rows":null},{"label":"Email","value":"b","type":"email","required":true,"rows":null},{"label":"Phone No","value":"c","type":"number","required":false,"rows":null},{"label":"Password","value":"d","type":"password","required":true,"rows":null}],"formValue":{"a":"","b":"","c":"","d":""},"payload":"","submit":"submit","cancel":"cancel","topic":"","x":239,"y":269,"wires":[["5c282aca.7411a4","dac5757c.95ff48"]]},{"id":"617960c6.f84cd","type":"ui_group","z":"","name":"group1","tab":"912cec9.7bf021","order":1,"disp":true,"width":"6","collapse":false},{"id":"912cec9.7bf021","type":"ui_tab","z":"","name":"Home","icon":"dashboard","order":1,"disabled":false,"hidden":false}]